dbnd_spark/__init__.py
dbnd_spark/_plugin.py
dbnd_spark/spark.py
dbnd_spark/spark_bootstrap.py
dbnd_spark/spark_config.py
dbnd_spark/spark_ctrl.py
dbnd_spark/spark_session.py
dbnd_spark/_core/__init__.py
dbnd_spark/_core/spark_error_parser.py
dbnd_spark/_vendor/__init__.py
dbnd_spark/_vendor/airflow/LICENSE
dbnd_spark/_vendor/airflow/__init__.py
dbnd_spark/_vendor/airflow/connection.py
dbnd_spark/_vendor/airflow/spark_hook.py
dbnd_spark/livy/__init__.py
dbnd_spark/livy/livy_batch.py
dbnd_spark/livy/livy_spark.py
dbnd_spark/livy/livy_spark_config.py
dbnd_spark/local/__init__.py
dbnd_spark/local/local_spark.py
dbnd_spark/local/local_spark_config.py
dbnd_spark/spark_targets/__init__.py
dbnd_spark-1.0.30.1.dist-info/LICENSE
dbnd_spark-1.0.30.1.dist-info/METADATA
dbnd_spark-1.0.30.1.dist-info/WHEEL
dbnd_spark-1.0.30.1.dist-info/entry_points.txt
dbnd_spark-1.0.30.1.dist-info/top_level.txt
dbnd_spark-1.0.30.1.dist-info/RECORD
